[{"model": "admin.logentry", "pk": 1, "fields": {"action_time": "2024-01-20T10:47:15.321Z", "user": 1, "content_type": 14, "object_id": "1", "object_repr": "Ana səhifə slayder", "action_flag": 1, "change_message": "[{\"added\": {}}, {\"added\": {\"name\": \"\\u015e\\u0259kil\", \"object\": \"\\u015e\\u0259kil 1\"}}]"}}, {"model": "admin.logentry", "pk": 2, "fields": {"action_time": "2024-01-20T10:47:45.079Z", "user": 1, "content_type": 14, "object_id": "1", "object_repr": "Ana səhifə slayder", "action_flag": 2, "change_message": "[{\"changed\": {\"name\": \"\\u015e\\u0259kil\", \"object\": \"\\u015e\\u0259kil 1\", \"fields\": [\"Image\"]}}]"}}, {"model": "admin.logentry", "pk": 3, "fields": {"action_time": "2024-01-20T10:51:45.371Z", "user": 1, "content_type": 11, "object_id": "1", "object_repr": "Oftalmoloq cərrah Gülşən Dikmen", "action_flag": 1, "change_message": "[{\"added\": {}}, {\"added\": {\"name\": \"work hour\", \"object\": \"Bazar ert\\u0259si - C\\u00fcm\\u0259: 09:00 - 18:00\"}}, {\"added\": {\"name\": \"work hour\", \"object\": \"\\u015e\\u0259nb\\u0259: 10:00-17:00\"}}]"}}, {"model": "admin.logentry", "pk": 4, "fields": {"action_time": "2024-01-20T10:54:38.593Z", "user": 1, "content_type": 7, "object_id": "1", "object_repr": "Haqqımızda", "action_flag": 1, "change_message": "[{\"added\": {}}, {\"added\": {\"name\": \"Missiya\", \"object\": \"Y\\u00fcks\\u0259k keyfiyy\\u0259tli i\\u015f\"}}, {\"added\": {\"name\": \"Missiya\", \"object\": \"M\\u00fcnasib qiym\\u0259t\"}}, {\"added\": {\"name\": \"Missiya\", \"object\": \"S\\u00fcr\\u0259tli cavabland\\u0131rma\"}}, {\"added\": {\"name\": \"Vizyon\", \"object\": \"T\\u0259cili tibbi m\\u00fcdaxil\\u0259\"}}, {\"added\": {\"name\": \"Vizyon\", \"object\": \"G\\u00f6rm\\u0259nin b\\u0259rpas\\u0131\"}}]"}}, {"model": "admin.logentry", "pk": 5, "fields": {"action_time": "2024-01-20T10:56:44.971Z", "user": 1, "content_type": 16, "object_id": "1", "object_repr": "Femtosaniyə Lazer", "action_flag": 1, "change_message": "[{\"added\": {}}]"}}, {"model": "admin.logentry", "pk": 6, "fields": {"action_time": "2024-01-20T10:59:17.401Z", "user": 1, "content_type": 16, "object_id": "2", "object_repr": "Retina xəstəlikləri", "action_flag": 1, "change_message": "[{\"added\": {}}]"}}, {"model": "admin.logentry", "pk": 7, "fields": {"action_time": "2024-01-20T10:59:46.779Z", "user": 1, "content_type": 16, "object_id": "2", "object_repr": "Retina xəstəlikləri", "action_flag": 2, "change_message": "[{\"changed\": {\"fields\": [\"Is home page\"]}}]"}}, {"model": "admin.logentry", "pk": 8, "fields": {"action_time": "2024-01-20T11:01:59.010Z", "user": 1, "content_type": 16, "object_id": "3", "object_repr": "Çəpgözlük", "action_flag": 1, "change_message": "[{\"added\": {}}]"}}, {"model": "admin.logentry", "pk": 9, "fields": {"action_time": "2024-01-20T11:03:08.503Z", "user": 1, "content_type": 16, "object_id": "4", "object_repr": "Kataraktanın müalicəsi", "action_flag": 1, "change_message": "[{\"added\": {}}]"}}, {"model": "admin.logentry", "pk": 10, "fields": {"action_time": "2024-01-20T11:03:28.126Z", "user": 1, "content_type": 16, "object_id": "3", "object_repr": "Çəpgözlük əməliyyatı", "action_flag": 2, "change_message": "[{\"changed\": {\"fields\": [\"Title\"]}}]"}}, {"model": "admin.logentry", "pk": 11, "fields": {"action_time": "2024-01-20T11:05:11.556Z", "user": 1, "content_type": 16, "object_id": "5", "object_repr": "Refraktiv cərrahiyyə", "action_flag": 1, "change_message": "[{\"added\": {}}]"}}, {"model": "admin.logentry", "pk": 12, "fields": {"action_time": "2024-01-20T11:07:01.189Z", "user": 1, "content_type": 15, "object_id": "1", "object_repr": "Peşəkar həkim müayinəsi", "action_flag": 1, "change_message": "[{\"added\": {}}]"}}, {"model": "admin.logentry", "pk": 13, "fields": {"action_time": "2024-01-20T11:07:33.969Z", "user": 1, "content_type": 15, "object_id": "2", "object_repr": "Dəqiq diaqnoz", "action_flag": 1, "change_message": "[{\"added\": {}}]"}}, {"model": "admin.logentry", "pk": 14, "fields": {"action_time": "2024-01-20T11:07:58.064Z", "user": 1, "content_type": 15, "object_id": "3", "object_repr": "Fərdi yanaşma ilə müalicə", "action_flag": 1, "change_message": "[{\"added\": {}}]"}}, {"model": "admin.logentry", "pk": 15, "fields": {"action_time": "2024-01-20T11:09:24.917Z", "user": 1, "content_type": 10, "object_id": "1", "object_repr": "Statistika", "action_flag": 1, "change_message": "[{\"added\": {}}]"}}, {"model": "admin.logentry", "pk": 16, "fields": {"action_time": "2024-01-20T11:14:29.940Z", "user": 1, "content_type": 9, "object_id": "1", "object_repr": "Göz infeksiyaları yoluxucudur?", "action_flag": 1, "change_message": "[{\"added\": {}}]"}}, {"model": "admin.logentry", "pk": 17, "fields": {"action_time": "2024-01-20T11:14:49.784Z", "user": 1, "content_type": 9, "object_id": "2", "object_repr": "Körpə uşaqlarda göz zəifliyini necə hiss etmək olar?", "action_flag": 1, "change_message": "[{\"added\": {}}]"}}, {"model": "admin.logentry", "pk": 18, "fields": {"action_time": "2024-01-20T11:15:09.135Z", "user": 1, "content_type": 9, "object_id": "3", "object_repr": "Gözlərdə tez-tez olan yanma və qaşıntı nəyin əlamətidir?", "action_flag": 1, "change_message": "[{\"added\": {}}]"}}, {"model": "admin.logentry", "pk": 19, "fields": {"action_time": "2024-01-20T11:16:48.600Z", "user": 1, "content_type": 12, "object_id": "1", "object_repr": "Ana səhifə", "action_flag": 1, "change_message": "[{\"added\": {}}]"}}, {"model": "admin.logentry", "pk": 20, "fields": {"action_time": "2024-01-20T11:18:25.455Z", "user": 1, "content_type": 8, "object_id": "1", "object_repr": "Xanım Həsənova", "action_flag": 1, "change_message": "[{\"added\": {}}]"}}, {"model": "admin.logentry", "pk": 21, "fields": {"action_time": "2024-01-20T11:19:10.527Z", "user": 1, "content_type": 8, "object_id": "2", "object_repr": "Həsən Əliyev", "action_flag": 1, "change_message": "[{\"added\": {}}]"}}, {"model": "admin.logentry", "pk": 22, "fields": {"action_time": "2024-01-20T11:19:42.284Z", "user": 1, "content_type": 8, "object_id": "3", "object_repr": "Vəli Məmmədov", "action_flag": 1, "change_message": "[{\"added\": {}}]"}}, {"model": "admin.logentry", "pk": 23, "fields": {"action_time": "2024-01-20T11:22:22.156Z", "user": 1, "content_type": 23, "object_id": "1", "object_repr": "Gözdə yanma, qaşınma varsa, bunları edin!", "action_flag": 1, "change_message": "[{\"added\": {}}]"}}, {"model": "admin.logentry", "pk": 24, "fields": {"action_time": "2024-01-20T11:26:19.754Z", "user": 1, "content_type": 23, "object_id": "1", "object_repr": "Gözdə yanma, qaşınma varsa, bunları edin!", "action_flag": 2, "change_message": "[{\"changed\": {\"fields\": [\"Image\"]}}]"}}, {"model": "admin.logentry", "pk": 25, "fields": {"action_time": "2024-01-20T11:28:09.440Z", "user": 1, "content_type": 23, "object_id": "2", "object_repr": "Linzalardan düzgün istifadə qaydaları!", "action_flag": 1, "change_message": "[{\"added\": {}}]"}}, {"model": "admin.logentry", "pk": 26, "fields": {"action_time": "2024-01-20T11:29:37.589Z", "user": 1, "content_type": 23, "object_id": "3", "object_repr": "Qara su xəstəliyinin əlamətləri l Qlaukoma", "action_flag": 1, "change_message": "[{\"added\": {}}]"}}, {"model": "admin.logentry", "pk": 27, "fields": {"action_time": "2024-01-20T11:32:12.662Z", "user": 1, "content_type": 23, "object_id": "4", "object_repr": "Çəpgözlər iki yox, bir görürlər! l Uşaqlarda çəplik", "action_flag": 1, "change_message": "[{\"added\": {}}]"}}, {"model": "admin.logentry", "pk": 28, "fields": {"action_time": "2024-01-20T11:33:43.275Z", "user": 1, "content_type": 23, "object_id": "5", "object_repr": "Uşaqlarda gizli çəplik əlamətlərinə diqqət!", "action_flag": 1, "change_message": "[{\"added\": {}}]"}}, {"model": "admin.logentry", "pk": 29, "fields": {"action_time": "2024-01-20T11:35:11.300Z", "user": 1, "content_type": 23, "object_id": "6", "object_repr": "Göz əməliyyatları içində ən yaxşısı: \"SMİLE\"", "action_flag": 1, "change_message": "[{\"added\": {}}]"}}, {"model": "admin.logentry", "pk": 30, "fields": {"action_time": "2024-01-20T11:37:49.198Z", "user": 1, "content_type": 11, "object_id": "1", "object_repr": "Oftalmoloq cərrah Gülşən Dikmen", "action_flag": 2, "change_message": "[{\"changed\": {\"fields\": [\"S\\u0259hifl\\u0259rd\\u0259ki banner photo\"]}}]"}}, {"model": "admin.logentry", "pk": 31, "fields": {"action_time": "2024-01-20T11:42:39.130Z", "user": 1, "content_type": 13, "object_id": "1", "object_repr": "Əlaqə", "action_flag": 1, "change_message": "[{\"added\": {}}]"}}, {"model": "admin.logentry", "pk": 32, "fields": {"action_time": "2024-01-22T05:11:43.214Z", "user": 1, "content_type": 17, "object_id": "1", "object_repr": "Katarakta, mirvari suyu adlanan xəstəlik", "action_flag": 1, "change_message": "[{\"added\": {}}]"}}, {"model": "admin.logentry", "pk": 33, "fields": {"action_time": "2024-01-22T05:13:27.954Z", "user": 1, "content_type": 17, "object_id": "2", "object_repr": "Göz çəpliyinin səbəbi, çəpgözlük", "action_flag": 1, "change_message": "[{\"added\": {}}]"}}, {"model": "admin.logentry", "pk": 34, "fields": {"action_time": "2024-01-22T05:13:28.154Z", "user": 1, "content_type": 17, "object_id": "3", "object_repr": "Göz çəpliyinin səbəbi, çəpgözlük", "action_flag": 1, "change_message": "[{\"added\": {}}]"}}, {"model": "admin.logentry", "pk": 35, "fields": {"action_time": "2024-01-22T05:13:50.704Z", "user": 1, "content_type": 17, "object_id": "3", "object_repr": "Göz çəpliyinin səbəbi, çəpgözlük", "action_flag": 3, "change_message": ""}}, {"model": "admin.logentry", "pk": 36, "fields": {"action_time": "2024-01-22T07:47:35.543Z", "user": 1, "content_type": 17, "object_id": "4", "object_repr": "Uşaqlarda göz xəstəlikləri", "action_flag": 1, "change_message": "[{\"added\": {}}]"}}, {"model": "admin.logentry", "pk": 37, "fields": {"action_time": "2024-01-22T07:49:23.130Z", "user": 1, "content_type": 17, "object_id": "5", "object_repr": "Miopiya, miopiyanın qarşısını almaq mümkündürmü?", "action_flag": 1, "change_message": "[{\"added\": {}}]"}}, {"model": "admin.logentry", "pk": 38, "fields": {"action_time": "2024-01-22T08:08:37.654Z", "user": 1, "content_type": 7, "object_id": "1", "object_repr": "Haqqımızda", "action_flag": 2, "change_message": "[{\"changed\": {\"name\": \"Missiya\", \"object\": \"Pasiyentl\\u0259rin komfortu\", \"fields\": [\"Title\"]}}, {\"changed\": {\"name\": \"Missiya\", \"object\": \"Effektiv m\\u00fcalic\\u0259\", \"fields\": [\"Title\"]}}, {\"changed\": {\"name\": \"Missiya\", \"object\": \"U\\u011furlu n\\u0259tic\\u0259\", \"fields\": [\"Title\"]}}, {\"changed\": {\"name\": \"Vizyon\", \"object\": \"Sa\\u011flam g\\u00f6zl\\u0259r\", \"fields\": [\"Title\"]}}, {\"changed\": {\"name\": \"Vizyon\", \"object\": \"Xo\\u015fb\\u0259xt pasiyentl\\u0259r\", \"fields\": [\"Title\"]}}]"}}, {"model": "admin.logentry", "pk": 39, "fields": {"action_time": "2024-01-22T08:09:10.482Z", "user": 1, "content_type": 7, "object_id": "1", "object_repr": "Haqqımızda", "action_flag": 2, "change_message": "[{\"changed\": {\"name\": \"Missiya\", \"object\": \"Pasiyent komfortu\", \"fields\": [\"Title\"]}}]"}}, {"model": "admin.logentry", "pk": 40, "fields": {"action_time": "2024-01-22T08:12:37.965Z", "user": 1, "content_type": 7, "object_id": "1", "object_repr": "Haqqımızda", "action_flag": 2, "change_message": "[{\"changed\": {\"name\": \"Vizyon\", \"object\": \"M\\u0259mnun pasiyentl\\u0259r\", \"fields\": [\"Title\"]}}]"}}, {"model": "admin.logentry", "pk": 41, "fields": {"action_time": "2024-01-22T09:09:16.561Z", "user": 1, "content_type": 17, "object_id": "1", "object_repr": "Katarakta, mirvari suyu adlanan xəstəlik", "action_flag": 2, "change_message": "[{\"changed\": {\"fields\": [\"Image\", \"Is home page\"]}}]"}}, {"model": "admin.logentry", "pk": 42, "fields": {"action_time": "2024-01-22T09:09:34.354Z", "user": 1, "content_type": 17, "object_id": "2", "object_repr": "Göz çəpliyinin səbəbi, çəpgözlük", "action_flag": 2, "change_message": "[{\"changed\": {\"fields\": [\"Image\", \"Is home page\"]}}]"}}, {"model": "admin.logentry", "pk": 43, "fields": {"action_time": "2024-01-22T09:10:05.753Z", "user": 1, "content_type": 17, "object_id": "4", "object_repr": "Uşaqlarda göz xəstəlikləri", "action_flag": 2, "change_message": "[{\"changed\": {\"fields\": [\"Image\", \"Is home page\"]}}]"}}, {"model": "admin.logentry", "pk": 44, "fields": {"action_time": "2024-01-22T09:11:50.836Z", "user": 1, "content_type": 17, "object_id": "1", "object_repr": "Katarakta, mirvari suyu adlanan xəstəlik", "action_flag": 2, "change_message": "[{\"changed\": {\"fields\": [\"Image\"]}}]"}}, {"model": "admin.logentry", "pk": 45, "fields": {"action_time": "2024-01-22T09:12:02.964Z", "user": 1, "content_type": 17, "object_id": "2", "object_repr": "Göz çəpliyinin səbəbi, çəpgözlük", "action_flag": 2, "change_message": "[{\"changed\": {\"fields\": [\"Image\"]}}]"}}, {"model": "admin.logentry", "pk": 46, "fields": {"action_time": "2024-01-22T09:12:13.604Z", "user": 1, "content_type": 17, "object_id": "4", "object_repr": "Uşaqlarda göz xəstəlikləri", "action_flag": 2, "change_message": "[{\"changed\": {\"fields\": [\"Image\"]}}]"}}, {"model": "admin.logentry", "pk": 47, "fields": {"action_time": "2024-01-22T09:12:26.889Z", "user": 1, "content_type": 17, "object_id": "5", "object_repr": "Miopiya, miopiyanın qarşısını almaq mümkündürmü?", "action_flag": 2, "change_message": "[{\"changed\": {\"fields\": [\"Image\"]}}]"}}, {"model": "admin.logentry", "pk": 48, "fields": {"action_time": "2024-01-22T10:42:05.418Z", "user": 1, "content_type": 17, "object_id": "1", "object_repr": "Katarakta, mirvari suyu adlanan xəstəlik", "action_flag": 2, "change_message": "[{\"changed\": {\"fields\": [\"Description 2\"]}}]"}}, {"model": "admin.logentry", "pk": 49, "fields": {"action_time": "2024-01-22T10:42:50.397Z", "user": 1, "content_type": 17, "object_id": "2", "object_repr": "Göz çəpliyinin səbəbi, çəpgözlük", "action_flag": 2, "change_message": "[{\"changed\": {\"fields\": [\"Description 2\"]}}]"}}, {"model": "admin.logentry", "pk": 50, "fields": {"action_time": "2024-01-22T10:43:06.684Z", "user": 1, "content_type": 17, "object_id": "4", "object_repr": "Uşaqlarda göz xəstəlikləri", "action_flag": 2, "change_message": "[{\"changed\": {\"fields\": [\"Description 2\"]}}]"}}, {"model": "admin.logentry", "pk": 51, "fields": {"action_time": "2024-01-22T10:43:25.346Z", "user": 1, "content_type": 17, "object_id": "5", "object_repr": "Miopiya, miopiyanın qarşısını almaq mümkündürmü?", "action_flag": 2, "change_message": "[{\"changed\": {\"fields\": [\"Description 2\"]}}]"}}, {"model": "auth.permission", "pk": 1, "fields": {"name": "Can add log entry", "content_type": 1, "codename": "add_logentry"}}, {"model": "auth.permission", "pk": 2, "fields": {"name": "Can change log entry", "content_type": 1, "codename": "change_logentry"}}, {"model": "auth.permission", "pk": 3, "fields": {"name": "Can delete log entry", "content_type": 1, "codename": "delete_logentry"}}, {"model": "auth.permission", "pk": 4, "fields": {"name": "Can view log entry", "content_type": 1, "codename": "view_logentry"}}, {"model": "auth.permission", "pk": 5, "fields": {"name": "Can add permission", "content_type": 2, "codename": "add_permission"}}, {"model": "auth.permission", "pk": 6, "fields": {"name": "Can change permission", "content_type": 2, "codename": "change_permission"}}, {"model": "auth.permission", "pk": 7, "fields": {"name": "Can delete permission", "content_type": 2, "codename": "delete_permission"}}, {"model": "auth.permission", "pk": 8, "fields": {"name": "Can view permission", "content_type": 2, "codename": "view_permission"}}, {"model": "auth.permission", "pk": 9, "fields": {"name": "Can add group", "content_type": 3, "codename": "add_group"}}, {"model": "auth.permission", "pk": 10, "fields": {"name": "Can change group", "content_type": 3, "codename": "change_group"}}, {"model": "auth.permission", "pk": 11, "fields": {"name": "Can delete group", "content_type": 3, "codename": "delete_group"}}, {"model": "auth.permission", "pk": 12, "fields": {"name": "Can view group", "content_type": 3, "codename": "view_group"}}, {"model": "auth.permission", "pk": 13, "fields": {"name": "Can add user", "content_type": 4, "codename": "add_user"}}, {"model": "auth.permission", "pk": 14, "fields": {"name": "Can change user", "content_type": 4, "codename": "change_user"}}, {"model": "auth.permission", "pk": 15, "fields": {"name": "Can delete user", "content_type": 4, "codename": "delete_user"}}, {"model": "auth.permission", "pk": 16, "fields": {"name": "Can view user", "content_type": 4, "codename": "view_user"}}, {"model": "auth.permission", "pk": 17, "fields": {"name": "Can add content type", "content_type": 5, "codename": "add_contenttype"}}, {"model": "auth.permission", "pk": 18, "fields": {"name": "Can change content type", "content_type": 5, "codename": "change_contenttype"}}, {"model": "auth.permission", "pk": 19, "fields": {"name": "Can delete content type", "content_type": 5, "codename": "delete_contenttype"}}, {"model": "auth.permission", "pk": 20, "fields": {"name": "Can view content type", "content_type": 5, "codename": "view_contenttype"}}, {"model": "auth.permission", "pk": 21, "fields": {"name": "Can add session", "content_type": 6, "codename": "add_session"}}, {"model": "auth.permission", "pk": 22, "fields": {"name": "Can change session", "content_type": 6, "codename": "change_session"}}, {"model": "auth.permission", "pk": 23, "fields": {"name": "Can delete session", "content_type": 6, "codename": "delete_session"}}, {"model": "auth.permission", "pk": 24, "fields": {"name": "Can view session", "content_type": 6, "codename": "view_session"}}, {"model": "auth.permission", "pk": 25, "fields": {"name": "Can add Haqqımızda", "content_type": 7, "codename": "add_aboutpage"}}, {"model": "auth.permission", "pk": 26, "fields": {"name": "Can change Haqqımızda", "content_type": 7, "codename": "change_aboutpage"}}, {"model": "auth.permission", "pk": 27, "fields": {"name": "Can delete Haqqımızda", "content_type": 7, "codename": "delete_aboutpage"}}, {"model": "auth.permission", "pk": 28, "fields": {"name": "Can view Haqqımızda", "content_type": 7, "codename": "view_aboutpage"}}, {"model": "auth.permission", "pk": 29, "fields": {"name": "Can add Müştəri rəyi", "content_type": 8, "codename": "add_customercomment"}}, {"model": "auth.permission", "pk": 30, "fields": {"name": "Can change Müştəri rəyi", "content_type": 8, "codename": "change_customercomment"}}, {"model": "auth.permission", "pk": 31, "fields": {"name": "Can delete Müştəri rəyi", "content_type": 8, "codename": "delete_customercomment"}}, {"model": "auth.permission", "pk": 32, "fields": {"name": "Can view Müştəri rəyi", "content_type": 8, "codename": "view_customercomment"}}, {"model": "auth.permission", "pk": 33, "fields": {"name": "Can add Sual", "content_type": 9, "codename": "add_faq"}}, {"model": "auth.permission", "pk": 34, "fields": {"name": "Can change Sual", "content_type": 9, "codename": "change_faq"}}, {"model": "auth.permission", "pk": 35, "fields": {"name": "Can delete Sual", "content_type": 9, "codename": "delete_faq"}}, {"model": "auth.permission", "pk": 36, "fields": {"name": "Can view Sual", "content_type": 9, "codename": "view_faq"}}, {"model": "auth.permission", "pk": 37, "fields": {"name": "Can add Statistika", "content_type": 10, "codename": "add_funfact"}}, {"model": "auth.permission", "pk": 38, "fields": {"name": "Can change Statistika", "content_type": 10, "codename": "change_funfact"}}, {"model": "auth.permission", "pk": 39, "fields": {"name": "Can delete Statistika", "content_type": 10, "codename": "delete_funfact"}}, {"model": "auth.permission", "pk": 40, "fields": {"name": "Can view Statistika", "content_type": 10, "codename": "view_funfact"}}, {"model": "auth.permission", "pk": 41, "fields": {"name": "Can add Setting", "content_type": 11, "codename": "add_generalsettings"}}, {"model": "auth.permission", "pk": 42, "fields": {"name": "Can change Setting", "content_type": 11, "codename": "change_generalsettings"}}, {"model": "auth.permission", "pk": 43, "fields": {"name": "Can delete Setting", "content_type": 11, "codename": "delete_generalsettings"}}, {"model": "auth.permission", "pk": 44, "fields": {"name": "Can view Setting", "content_type": 11, "codename": "view_generalsettings"}}, {"model": "auth.permission", "pk": 45, "fields": {"name": "Can add Ana səhifə", "content_type": 12, "codename": "add_homepage"}}, {"model": "auth.permission", "pk": 46, "fields": {"name": "Can change Ana səhifə", "content_type": 12, "codename": "change_homepage"}}, {"model": "auth.permission", "pk": 47, "fields": {"name": "Can delete Ana səhifə", "content_type": 12, "codename": "delete_homepage"}}, {"model": "auth.permission", "pk": 48, "fields": {"name": "Can view Ana səhifə", "content_type": 12, "codename": "view_homepage"}}, {"model": "auth.permission", "pk": 49, "fields": {"name": "Can add Ana səhifə | Əlaqə hissəsi", "content_type": 13, "codename": "add_homepagecontactsection"}}, {"model": "auth.permission", "pk": 50, "fields": {"name": "Can change Ana səhifə | Əlaqə hissəsi", "content_type": 13, "codename": "change_homepagecontactsection"}}, {"model": "auth.permission", "pk": 51, "fields": {"name": "Can delete Ana səhifə | Əlaqə hissəsi", "content_type": 13, "codename": "delete_homepagecontactsection"}}, {"model": "auth.permission", "pk": 52, "fields": {"name": "Can view Ana səhifə | Əlaqə hissəsi", "content_type": 13, "codename": "view_homepagecontactsection"}}, {"model": "auth.permission", "pk": 53, "fields": {"name": "Can add Ana səhifə | Slayder", "content_type": 14, "codename": "add_homepageslider"}}, {"model": "auth.permission", "pk": 54, "fields": {"name": "Can change Ana səhifə | Slayder", "content_type": 14, "codename": "change_homepageslider"}}, {"model": "auth.permission", "pk": 55, "fields": {"name": "Can delete Ana səhifə | Slayder", "content_type": 14, "codename": "delete_homepageslider"}}, {"model": "auth.permission", "pk": 56, "fields": {"name": "Can view Ana səhifə | Slayder", "content_type": 14, "codename": "view_homepageslider"}}, {"model": "auth.permission", "pk": 57, "fields": {"name": "Can add Proses", "content_type": 15, "codename": "add_process"}}, {"model": "auth.permission", "pk": 58, "fields": {"name": "Can change Proses", "content_type": 15, "codename": "change_process"}}, {"model": "auth.permission", "pk": 59, "fields": {"name": "Can delete Proses", "content_type": 15, "codename": "delete_process"}}, {"model": "auth.permission", "pk": 60, "fields": {"name": "Can view Proses", "content_type": 15, "codename": "view_process"}}, {"model": "auth.permission", "pk": 61, "fields": {"name": "Can add Xidmət", "content_type": 16, "codename": "add_service"}}, {"model": "auth.permission", "pk": 62, "fields": {"name": "Can change Xidmət", "content_type": 16, "codename": "change_service"}}, {"model": "auth.permission", "pk": 63, "fields": {"name": "Can delete Xidmət", "content_type": 16, "codename": "delete_service"}}, {"model": "auth.permission", "pk": 64, "fields": {"name": "Can view Xidmət", "content_type": 16, "codename": "view_service"}}, {"model": "auth.permission", "pk": 65, "fields": {"name": "Can add Bloq", "content_type": 17, "codename": "add_blog"}}, {"model": "auth.permission", "pk": 66, "fields": {"name": "Can change Bloq", "content_type": 17, "codename": "change_blog"}}, {"model": "auth.permission", "pk": 67, "fields": {"name": "Can delete Bloq", "content_type": 17, "codename": "delete_blog"}}, {"model": "auth.permission", "pk": 68, "fields": {"name": "Can view Bloq", "content_type": 17, "codename": "view_blog"}}, {"model": "auth.permission", "pk": 69, "fields": {"name": "Can add Şəkil", "content_type": 18, "codename": "add_homepagesliderimage"}}, {"model": "auth.permission", "pk": 70, "fields": {"name": "Can change Şəkil", "content_type": 18, "codename": "change_homepagesliderimage"}}, {"model": "auth.permission", "pk": 71, "fields": {"name": "Can delete Şəkil", "content_type": 18, "codename": "delete_homepagesliderimage"}}, {"model": "auth.permission", "pk": 72, "fields": {"name": "Can view Şəkil", "content_type": 18, "codename": "view_homepagesliderimage"}}, {"model": "auth.permission", "pk": 73, "fields": {"name": "Can add Missiya", "content_type": 19, "codename": "add_ourmission"}}, {"model": "auth.permission", "pk": 74, "fields": {"name": "Can change Missiya", "content_type": 19, "codename": "change_ourmission"}}, {"model": "auth.permission", "pk": 75, "fields": {"name": "Can delete Missiya", "content_type": 19, "codename": "delete_ourmission"}}, {"model": "auth.permission", "pk": 76, "fields": {"name": "Can view Missiya", "content_type": 19, "codename": "view_ourmission"}}, {"model": "auth.permission", "pk": 77, "fields": {"name": "Can add Vizyon", "content_type": 20, "codename": "add_ourvision"}}, {"model": "auth.permission", "pk": 78, "fields": {"name": "Can change Vizyon", "content_type": 20, "codename": "change_ourvision"}}, {"model": "auth.permission", "pk": 79, "fields": {"name": "Can delete Vizyon", "content_type": 20, "codename": "delete_ourvision"}}, {"model": "auth.permission", "pk": 80, "fields": {"name": "Can view Vizyon", "content_type": 20, "codename": "view_ourvision"}}, {"model": "auth.permission", "pk": 81, "fields": {"name": "Can add Punkt", "content_type": 21, "codename": "add_servicepunkt"}}, {"model": "auth.permission", "pk": 82, "fields": {"name": "Can change Punkt", "content_type": 21, "codename": "change_servicepunkt"}}, {"model": "auth.permission", "pk": 83, "fields": {"name": "Can delete Punkt", "content_type": 21, "codename": "delete_servicepunkt"}}, {"model": "auth.permission", "pk": 84, "fields": {"name": "Can view Punkt", "content_type": 21, "codename": "view_servicepunkt"}}, {"model": "auth.permission", "pk": 85, "fields": {"name": "Can add work hour", "content_type": 22, "codename": "add_workhour"}}, {"model": "auth.permission", "pk": 86, "fields": {"name": "Can change work hour", "content_type": 22, "codename": "change_workhour"}}, {"model": "auth.permission", "pk": 87, "fields": {"name": "Can delete work hour", "content_type": 22, "codename": "delete_workhour"}}, {"model": "auth.permission", "pk": 88, "fields": {"name": "Can view work hour", "content_type": 22, "codename": "view_workhour"}}, {"model": "auth.permission", "pk": 89, "fields": {"name": "Can add Qaleriya", "content_type": 23, "codename": "add_gallery"}}, {"model": "auth.permission", "pk": 90, "fields": {"name": "Can change Qaleriya", "content_type": 23, "codename": "change_gallery"}}, {"model": "auth.permission", "pk": 91, "fields": {"name": "Can delete Qaleriya", "content_type": 23, "codename": "delete_gallery"}}, {"model": "auth.permission", "pk": 92, "fields": {"name": "Can view Qaleriya", "content_type": 23, "codename": "view_gallery"}}, {"model": "auth.permission", "pk": 93, "fields": {"name": "Can add Mesaj", "content_type": 24, "codename": "add_contact"}}, {"model": "auth.permission", "pk": 94, "fields": {"name": "Can change Mesaj", "content_type": 24, "codename": "change_contact"}}, {"model": "auth.permission", "pk": 95, "fields": {"name": "Can delete Mesaj", "content_type": 24, "codename": "delete_contact"}}, {"model": "auth.permission", "pk": 96, "fields": {"name": "Can view Mesaj", "content_type": 24, "codename": "view_contact"}}, {"model": "auth.permission", "pk": 97, "fields": {"name": "Can add Görüş", "content_type": 25, "codename": "add_appointment"}}, {"model": "auth.permission", "pk": 98, "fields": {"name": "Can change Görüş", "content_type": 25, "codename": "change_appointment"}}, {"model": "auth.permission", "pk": 99, "fields": {"name": "Can delete Görüş", "content_type": 25, "codename": "delete_appointment"}}, {"model": "auth.permission", "pk": 100, "fields": {"name": "Can view Görüş", "content_type": 25, "codename": "view_appointment"}}, {"model": "auth.user", "pk": 1, "fields": {"password": "pbkdf2_sha256$720000$xUmM9UlyB0WLQWx6AP0bIi$CW7rraQgEluiJ05n19DqV5amBLaVvgk/D4NGoVaNY4Q=", "last_login": "2024-01-22T10:39:12.087Z", "is_superuser": true, "username": "admin", "first_name": "", "last_name": "", "email": "", "is_staff": true, "is_active": true, "date_joined": "2024-01-20T10:34:35.569Z", "groups": [], "user_permissions": []}}, {"model": "contenttypes.contenttype", "pk": 1, "fields": {"app_label": "admin", "model": "logentry"}}, {"model": "contenttypes.contenttype", "pk": 2, "fields": {"app_label": "auth", "model": "permission"}}, {"model": "contenttypes.contenttype", "pk": 3, "fields": {"app_label": "auth", "model": "group"}}, {"model": "contenttypes.contenttype", "pk": 4, "fields": {"app_label": "auth", "model": "user"}}, {"model": "contenttypes.contenttype", "pk": 5, "fields": {"app_label": "contenttypes", "model": "contenttype"}}, {"model": "contenttypes.contenttype", "pk": 6, "fields": {"app_label": "sessions", "model": "session"}}, {"model": "contenttypes.contenttype", "pk": 7, "fields": {"app_label": "core", "model": "aboutpage"}}, {"model": "contenttypes.contenttype", "pk": 8, "fields": {"app_label": "core", "model": "customercomment"}}, {"model": "contenttypes.contenttype", "pk": 9, "fields": {"app_label": "core", "model": "faq"}}, {"model": "contenttypes.contenttype", "pk": 10, "fields": {"app_label": "core", "model": "funfact"}}, {"model": "contenttypes.contenttype", "pk": 11, "fields": {"app_label": "core", "model": "generalsettings"}}, {"model": "contenttypes.contenttype", "pk": 12, "fields": {"app_label": "core", "model": "homepage"}}, {"model": "contenttypes.contenttype", "pk": 13, "fields": {"app_label": "core", "model": "homepagecontactsection"}}, {"model": "contenttypes.contenttype", "pk": 14, "fields": {"app_label": "core", "model": "homepageslider"}}, {"model": "contenttypes.contenttype", "pk": 15, "fields": {"app_label": "core", "model": "process"}}, {"model": "contenttypes.contenttype", "pk": 16, "fields": {"app_label": "core", "model": "service"}}, {"model": "contenttypes.contenttype", "pk": 17, "fields": {"app_label": "core", "model": "blog"}}, {"model": "contenttypes.contenttype", "pk": 18, "fields": {"app_label": "core", "model": "homepagesliderimage"}}, {"model": "contenttypes.contenttype", "pk": 19, "fields": {"app_label": "core", "model": "ourmission"}}, {"model": "contenttypes.contenttype", "pk": 20, "fields": {"app_label": "core", "model": "ourvision"}}, {"model": "contenttypes.contenttype", "pk": 21, "fields": {"app_label": "core", "model": "servicepunkt"}}, {"model": "contenttypes.contenttype", "pk": 22, "fields": {"app_label": "core", "model": "workhour"}}, {"model": "contenttypes.contenttype", "pk": 23, "fields": {"app_label": "core", "model": "gallery"}}, {"model": "contenttypes.contenttype", "pk": 24, "fields": {"app_label": "core", "model": "contact"}}, {"model": "contenttypes.contenttype", "pk": 25, "fields": {"app_label": "core", "model": "appointment"}}, {"model": "sessions.session", "pk": "8ul6fi6oyredlufqxveakjpmyk3elq4a", "fields": {"session_data": ".eJxVjEEOwiAURO_C2hCgfLEu3XsG8vkMUjVtUtqV8e7apAvdzntvXiryutS4NsxxyOqsrDr8bonlgXED-c7jbdIyjcs8JL0peqdNX6eM52V3_w4qt_qtC8j1jgEqXvoOJ0scIIDvfcqJijHs0QXvyAdX2FhIJ0cI2eDIsXp_AAOHOFs:1rRrhw:eRJjyrsyd70BJo6-k6hPoVAOR-ggNpuf1C_QDOthSG4", "expire_date": "2024-02-05T10:39:12.092Z"}}, {"model": "sessions.session", "pk": "fdn0dhawaxtnbj3skvnu3wv8gky5byy8", "fields": {"session_data": ".eJxVjEEOwiAURO_C2hCgfLEu3XsG8vkMUjVtUtqV8e7apAvdzntvXiryutS4NsxxyOqsrDr8bonlgXED-c7jbdIyjcs8JL0peqdNX6eM52V3_w4qt_qtC8j1jgEqXvoOJ0scIIDvfcqJijHs0QXvyAdX2FhIJ0cI2eDIsXp_AAOHOFs:1rR8gZ:DktwyedW57do25ndh2wk4dzxWQILf4S3mVJaHcrEFrs", "expire_date": "2024-02-03T10:34:47.491Z"}}, {"model": "sessions.session", "pk": "lul3rd1j5q2ngzz7dz4ecnmdmtgq7c12", "fields": {"session_data": ".eJxVjEEOwiAURO_C2hCgfLEu3XsG8vkMUjVtUtqV8e7apAvdzntvXiryutS4NsxxyOqsrDr8bonlgXED-c7jbdIyjcs8JL0peqdNX6eM52V3_w4qt_qtC8j1jgEqXvoOJ0scIIDvfcqJijHs0QXvyAdX2FhIJ0cI2eDIsXp_AAOHOFs:1rR9AN:IUwfSTKf1hJ_AraRHtAAXuDBNfNhkXTde7RX_4QoXoU", "expire_date": "2024-02-03T11:05:35.266Z"}}, {"model": "sessions.session", "pk": "owt933djufo4ftd4qc5g3u5783og45c7", "fields": {"session_data": ".eJxVjEEOwiAURO_C2hCgfLEu3XsG8vkMUjVtUtqV8e7apAvdzntvXiryutS4NsxxyOqsrDr8bonlgXED-c7jbdIyjcs8JL0peqdNX6eM52V3_w4qt_qtC8j1jgEqXvoOJ0scIIDvfcqJijHs0QXvyAdX2FhIJ0cI2eDIsXp_AAOHOFs:1rRmYk:PsQpQv-2uMidbqqWJlKDFwg3fB5W6MvhXGtuaiebEHI", "expire_date": "2024-02-05T05:09:22.647Z"}}, {"model": "sessions.session", "pk": "s2ok7vni7mfxtfe2qk7vdendc7az6se1", "fields": {"session_data": ".eJxVjEEOwiAURO_C2hCgfLEu3XsG8vkMUjVtUtqV8e7apAvdzntvXiryutS4NsxxyOqsrDr8bonlgXED-c7jbdIyjcs8JL0peqdNX6eM52V3_w4qt_qtC8j1jgEqXvoOJ0scIIDvfcqJijHs0QXvyAdX2FhIJ0cI2eDIsXp_AAOHOFs:1rR8lH:5TMK_L942_y3ejounxRPrtecPhvYSoxuqPg7hh8HEwc", "expire_date": "2024-02-03T10:39:39.772Z"}}, {"model": "core.generalsettings", "pk": 1, "fields": {"site_title": "Oftalmoloq cərrah Gülşən Dikmen", "adress": "13a Abbasgulu Abbaszadeh, Baku 1004", "phone_number": "+994 55 352 55 77", "email": "info@gulshandikmen.az", "g_adress": "https://maps.app.goo.gl/SGe6fzD7RaMXtDWYA", "g_adress_iframe": "https://www.google.com/maps/embed?pb=!1m18!1m12!1m3!1d3040.542860484949!2d49.81076947490385!3d40.352485859548686!2m3!1f0!2f0!3f0!3m2!1i1024!2i768!4f13.1!3m3!1m2!1s0x40307db0c39317b3%3A0xb52d33aedaccc54d!2sBadam%20Medical%20Center!5e0!3m2!1sen!2saz!4v1705747781500!5m2!1sen!2saz", "logo": "general_settings_logo/Oftalmoloq_cərrah_gülşən_dikmen.png", "mobile_logo": "general_settings_mobile_logo/Oftalmoloq_cərrah_gülşən_dikmen.png", "favicon": "general_settings_favicon/Oftalmoloq_cərrah_gülşən_dikmen.png", "footer_logo": "general_settings_footer_logo/Oftalmoloq_cərrah_gülşən_dikmen.png", "footer_description": "Əsasən Türkiyədə və Hindistanda ixtisaslaşan, 15 ildən artıq təcrübəyə malik olan oftalmoloq-cərrah Gülşən Dikmen hal-hazırda Badam Medical Center, Nur Göz Mərkəzində çalışır.", "copyright_title": "vrproduction.az", "pages_banner_image": "banner_image/Başlıqsız_dizayn_16.png", "facebook": "https://www.facebook.com/drgulshendikmen", "instagram": "https://www.instagram.com/drgulshendikmen/", "youtube": "https://www.youtube.com/@drgulshendikmen", "tiktok": "https://www.tiktok.com/@drgulshendikmen"}}, {"model": "core.workhour", "pk": 1, "fields": {"week_day": "Bazar ertəsi - Cümə", "hours": "09:00 - 18:00", "settings": 1}}, {"model": "core.workhour", "pk": 2, "fields": {"week_day": "Şənbə", "hours": "10:00-17:00", "settings": 1}}, {"model": "core.homepage", "pk": 1, "fields": {"consultancy_section_title": "Bizimlə əlaqə", "service_section_title": "Xidmətlər", "how_it_works_title": "Biz necə işləyirik?", "faq_big_image": "faq_big/Oftalmoloq_dr._Gülşən_Dikmen.png", "faq_small_image": "faq_small/verified.png", "customer_comment_title": "Pasiyent rəyləri", "blog_section_title": "Bloqlar"}}, {"model": "core.homepageslider", "pk": 1, "fields": {"title": "Oftalmoloq cərrah Gülşən Dikmen", "description": "Göz sağlamlığınızı bizə etibar edin"}}, {"model": "core.homepagesliderimage", "pk": 1, "fields": {"slider": 1, "image": "home_page_slider/Без_имени-3ef.png"}}, {"model": "core.aboutpage", "pk": 1, "fields": {"image": "about/Oftalmoloq_-_Göz_həkimi_Gülşən_Dikmen_2.png", "title": "Haqqımızda", "description": "Gülşən Dikmen Azərbaycan Tibb Universitetinin müalicə fakültəsində təhsil almışdır. 2008-ci ildə Akademik Zərifə Əliyeva adına E.T. Göz Xəstəlikləri İnstitutunda həkim-interna kimi təcrübə keçmişdir. Daha sonra Türkiyənin İzmir şəhərində oftalmoloq-assistent kimi çalışıb. 2012-2015-ci illərdə Hindistanda okuloplastik cərrahiyyə, müxtəlif göz xəstəliklərinin müalicəsini həyata keçirmişdir. O, Türkiyənin Adana şəhərində yerləşən Sevgi Göz xəstəxanasında Excimer Lazer göz əməliyyatlarını uğurla həyata keçirib. \r\n\r\nƏsasən Türkiyədə və Hindistanda ixtisaslaşan, 15 ildən artıq təcrübəyə malik olan oftalmoloq-cərrah Gülşən Dikmen hal-hazırda Badam Medical Center, Nur Göz Mərkəzində çalışır.", "experience": 15}}, {"model": "core.ourmission", "pk": 1, "fields": {"title": "Pasiyent komfortu", "about": 1}}, {"model": "core.ourmission", "pk": 2, "fields": {"title": "Effektiv müalicə", "about": 1}}, {"model": "core.ourmission", "pk": 3, "fields": {"title": "Uğurlu nəticə", "about": 1}}, {"model": "core.ourvision", "pk": 1, "fields": {"title": "Sağlam gözlər", "about": 1}}, {"model": "core.ourvision", "pk": 2, "fields": {"title": "Məmnun pasiyentlər", "about": 1}}, {"model": "core.service", "pk": 1, "fields": {"title": "Femtosaniyə Lazer", "slug": "femtosaniy-lazer", "icon": "service_icon/Oftalmoloq_-_Göz_həkimi_dr._Gülşən_dikmen.png", "image": "service/shutterstock_1175895889.webp", "description": "<p>Femtosaniyə Lazer ən təhl&uuml;kəsiz və risksiz lazer g&ouml;z əməliyyatı metodu hesab olunur. Əməliyyat sayəsində yaxşı g&ouml;rmək &uuml;&ccedil;&uuml;n eynək və linza istifadəsinə gərək qalmır. Femtosaniyə Lazer əməliyyatı bir ne&ccedil;ə dəqiqə ərzində uğurla icra olunur.&nbsp;</p>\r\n\r\n<p><br />\r\nTamamilə komp&uuml;ter texnologiyası nəzarəti altında olan bu sistem g&ouml;z əməliyyatını risksiz, bı&ccedil;aqsız və təmassız şəkildə həyata ke&ccedil;irir. Pasiyentin fərdi x&uuml;susiyyətləri və m&uuml;ayinə nəticələri sistemə daxil olduğundan bu metodla həyata ke&ccedil;irilən lazer əməliyyatı m&uuml;asir d&ouml;vr&uuml;n ən uğurlu g&ouml;z lazer əməliyyatıdır.</p>", "is_home_page": true}}, {"model": "core.service", "pk": 2, "fields": {"title": "Retina xəstəlikləri", "slug": "retina-xstliklri", "icon": "service_icon/Oftalmoloq_-_Göz_həkimi_dr._Gülşən_dikmen_YSoM2YK.png", "image": "service/shutterstock_1175895889_ZVTJJLD.webp", "description": "<p>diabet və y&uuml;ksək təzyiqi olan insanlarda rast gəlinən g&ouml;z xəstəlikləri<br />\r\nsarı n&ouml;qtə xəstəliyi&nbsp;<br />\r\nretina yırtılması<br />\r\nretina dekolmanı<br />\r\ng&ouml;zə yad cismin daxil olması və s. narahatlıqlar aiddir.&nbsp;</p>\r\n\r\n<p>G&ouml;z sinirləri yenilənmədiyi &uuml;&ccedil;&uuml;n retinada yaranan hər hansı problemin geri d&ouml;n&uuml;ş&uuml; yoxdur. Bu səbəbdən retina xəstəliklərinin erkən diaqnozu olduqca əhəmiyyətlidir.</p>", "is_home_page": true}}, {"model": "core.service", "pk": 3, "fields": {"title": "Çəpgözlük əməliyyatı", "slug": "cpgozluk-mliyyat", "icon": "service_icon/Oftalmoloq_-_Göz_həkimi_dr._Gülşən_dikmen_RRVY1ro.png", "image": "service/shutterstock_1175895889_FHHm798.webp", "description": "<p>&Ccedil;əpg&ouml;zl&uuml;k əsasən, uşaqlarda rast gəlinən və geniş yayılmış oftalmoloji patologiyadır.</p>\r\n\r\n<p>&Ccedil;əpg&ouml;zl&uuml;k estetik problem olmaqla yanaşı, g&ouml;zlərin normal fəaliyyətinə də mənfi təsir g&ouml;stərir. Belə ki, dəqiq g&ouml;rmə get-gedə pozulur və pasiyentin sterioskopik g&ouml;rmə qabiliyyəti itir. &nbsp;<br />\r\n&Ccedil;əpg&ouml;zl&uuml;k anadangəlmə və qazanılma səbəblərdən yarana bilər. Hər iki ehtimalda uşaqdan b&ouml;y&uuml;yə b&uuml;t&uuml;n insanlarda ağır kompleks yaradan bir g&ouml;z xəstəliyidir.</p>\r\n\r\n<p>&nbsp;</p>", "is_home_page": true}}, {"model": "core.service", "pk": 4, "fields": {"title": "Kataraktanın müalicəsi", "slug": "kataraktann-mualicsi", "icon": "service_icon/Oftalmoloq_-_Göz_həkimi_dr._Gülşən_dikmen_Vta5YPD.png", "image": "service/shutterstock_1175895889_g6fJaem.webp", "description": "<p>Katarakta &ndash; g&ouml;z b&uuml;lluru şəffaflığının pozulması deməkdir və yaşı 55-dən yuxarı olan insanlar arasında ən geniş yayılmış g&ouml;z xəstəliyidir. &Uuml;mumiyyətlə, hər bir insan &uuml;&ccedil;&uuml;n qocalıqda katarakta xəstəliyi riski var.</p>\r\n\r\n<p>Katarakta anadangəlmə bir xəstəlik kimi də g&ouml;r&uuml;lə bilir. Bu zaman başlıca məsələ kataraktanın erkən diaqnozlaşdırılmasıdır.</p>", "is_home_page": true}}, {"model": "core.service", "pk": 5, "fields": {"title": "Refraktiv cərrahiyyə", "slug": "refraktiv-crrahiyy", "icon": "service_icon/Oftalmoloq_-_Göz_həkimi_dr._Gülşən_dikmen_t88yoaY.png", "image": "service/shutterstock_1175895889_rOzIbQX.webp", "description": "<p>Refraktiv cərrahiyyə refraktiv q&uuml;surların - miopiya, astiqmatizm, hipermetropiya kimi g&ouml;z xəstəliklərinin m&uuml;alicə metodu kimi tətbiq olunur.</p>\r\n\r\n<p>Refraktiv cərrahiyyə ilə buynuz qişa əyriliyi d&uuml;zəldilir.</p>\r\n\r\n<p>Bu cərrahi prosedurlar kompleksi m&uuml;xtəlif g&ouml;z xəstəliklərinin m&uuml;alicəsində ən m&uuml;asir &uuml;sulları əhatə edir. Bu cərrahi prosedur əsasənn 18 yaşını ke&ccedil;miş şəxslərə tətbiq edilir.</p>", "is_home_page": true}}, {"model": "core.process", "pk": 1, "fields": {"image": "process/verified.png", "title": "Peşəkar həkim müayinəsi", "description": "Göz ən həssas orqanlarından biri olduğundan son dərəcə peşəkar və təcrübəli oftalmoloq tərəfindən xüsusi yanaşma tələb edir.", "sequence": 1}}, {"model": "core.process", "pk": 2, "fields": {"image": "process/verified_NwSCihf.png", "title": "Dəqiq diaqnoz", "description": "Göz xəstəliklərinin erkən mərhələdə və ən doğru şəkildə aşkarlanması pasiyentin görmə qabiliyyətinin itirilməsinin qarşısını alır.", "sequence": 2}}, {"model": "core.process", "pk": 3, "fields": {"image": "process/verified_2Q8kIIC.png", "title": "Fərdi yanaşma ilə müalicə", "description": "Hər bir fərdin bioloji xüsusiyyətlərinə uyğun hazırlanan və effektiv nəticə verən müalicə planı", "sequence": 3}}, {"model": "core.funfact", "pk": 1, "fields": {"experience": 15, "different_services": 9, "happy_patients": 10000, "article": 15}}, {"model": "core.faq", "pk": 1, "fields": {"title": "Göz infeksiyaları yoluxucudur?", "description": "Bəli, göz infeksiyaları insandan insana keçə bilir. Buna görə də çirkli əlləri gözə toxundurmaq və ya infeksiya olan insanlarla yaxın təmasda olmaq olmaz."}}, {"model": "core.faq", "pk": 2, "fields": {"title": "Körpə uşaqlarda göz zəifliyini necə hiss etmək olar?", "description": "Təəssüf ki, bunu valideynlər dəqiq anlaya bilmirlər. Yeni doğulmuş uşaqların 6-cı ayından artıq göz müayinələrinə aparmaq lazımdır."}}, {"model": "core.faq", "pk": 3, "fields": {"title": "Gözlərdə tez-tez olan yanma və qaşıntı nəyin əlamətidir?", "description": "Bu, allergik reaksiyalar da daxil olmaqla, bir çox göz xəstəliyinin əlaməti ola bilər."}}, {"model": "core.customercomment", "pk": 1, "fields": {"image": "customer_comments/girl.png", "full_name": "Xanım Həsənova", "text": "Mənim savadlı və gözəl həkimim, Allah sizdən razı olsun, sizə minnətdaram!"}}, {"model": "core.customercomment", "pk": 2, "fields": {"image": "customer_comments/man_1.png", "full_name": "Həsən Əliyev", "text": "Allah sizə can sağlığı versin. Sizin köməkliyiniz ilə şəfa tapdım."}}, {"model": "core.customercomment", "pk": 3, "fields": {"image": "customer_comments/Əliyev_Mahmud.png", "full_name": "Vəli Məmmədov", "text": "Çox sağ olun, oğlumu əməliyyat etdiniz. Çəpgözlükdən, kompleksdən azad oldu, artıq görünüşündən utanmır."}}, {"model": "core.homepagecontactsection", "pk": 1, "fields": {"section_title": "Əlaqə", "video_bg_image": "contact/Oftalmoloq_-.png", "youtube_link": "https://www.youtube.com/watch?v=CxyDhFhhLLE"}}, {"model": "core.blog", "pk": 1, "fields": {"title": "Katarakta, mirvari suyu adlanan xəstəlik", "description": "<p><span style=\"font-size:14pt\"><span style=\"font-family:&quot;Times New Roman&quot;,serif\"><strong><span style=\"font-size:18.0pt\">Mirvari suyu (Katarakta)&nbsp;</span></strong></span></span></p>\r\n\r\n<p><span style=\"font-size:14pt\"><span style=\"font-family:&quot;Times New Roman&quot;,serif\"><span style=\"font-size:12.0pt\">El arasında katarakta xəstəliyinə &quot;mirvari suyu&quot; adı verilmişdir. Bəs mirvari suyu və ya katarakta adlandırılan xəstəlik nədir? Katarakta - g&ouml;z&uuml;n şəffaf b&uuml;llurunun bulanması nəticəsində yaranır. Katarakta nəticəsində işıq ş&uuml;asının g&ouml;zə daxil olmasında maneələr yaranır və beləliklə, g&ouml;z zəifləyir. Bu halda b&uuml;llur &ouml;z şəffaflığını qismən və ya b&uuml;t&ouml;vl&uuml;kdə itirə bilər.</span></span></span></p>\r\n\r\n<p><span style=\"font-size:14pt\"><span style=\"font-family:&quot;Times New Roman&quot;,serif\"><span style=\"font-size:12.0pt\">Katarakta bir və ya hər iki g&ouml;zdə ortaya &ccedil;ıxa bilər.</span></span></span></p>\r\n\r\n<p><span style=\"font-size:14pt\"><span style=\"font-family:&quot;Times New Roman&quot;,serif\"><strong><span style=\"font-size:18.0pt\">Mirvari suyunun yaranma səbəbləri - katarakta səbəbləri</span></strong></span></span></p>\r\n\r\n<p><span style=\"font-size:14pt\"><span style=\"font-family:&quot;Times New Roman&quot;,serif\"><span style=\"font-size:12.0pt\">Katarakta bir ne&ccedil;ə səbəbdən meydana &ccedil;ıxa bilər; anadangəlmə, travmatik katarakta, qocalıqla bağlı yaranan katarakta və s.&nbsp;</span></span></span></p>\r\n\r\n<p style=\"text-align:justify\">&nbsp;</p>\r\n\r\n<h3><span style=\"font-size:12pt\"><span style=\"font-family:&quot;Calibri Light&quot;,sans-serif\"><span style=\"color:#1f4d78\"><strong><span style=\"font-family:&quot;Calibri Light&quot;,sans-serif\">Kataraktanın simptomları</span></strong></span></span></span></h3>\r\n\r\n<p><span style=\"font-size:12pt\"><span style=\"font-family:&quot;Times New Roman&quot;,serif\">Nəzərə almaq lazımdır ki, kataraktanın simptomlarının inkişafı b&uuml;llur bulanıqlarının harada yerləşməsi ilə bağlıdır. Belə ki, katarakta b&uuml;llurun kənar hissəsində yaranıbsa, pasiyentlər dəyişiklik hiss etməyə də bilir. Bulanma əlaməti b&uuml;llurun mərkəzinə nə qədər yaxın olarsa, g&ouml;rmə qabiliyyətində də bir o qədər problemlər ortaya &ccedil;ıxmış olur.</span></span></p>\r\n\r\n<p><span style=\"font-size:12pt\"><span style=\"font-family:&quot;Times New Roman&quot;,serif\">Siz bunu necə hiss edirsiniz? Belə ki,..</span></span></p>\r\n\r\n<p><span style=\"font-size:12pt\"><span style=\"font-family:&quot;Times New Roman&quot;,serif\">1) Ətrafınızdakı əşyaları dəqiq se&ccedil;ə (g&ouml;rə) bilmirsiniz, </span></span></p>\r\n\r\n<p><span style=\"font-size:12pt\"><span style=\"font-family:&quot;Times New Roman&quot;,serif\">2) torlu şəkildə (bulanıq) g&ouml;r&uuml;rs&uuml;n&uuml;z, </span></span></p>\r\n\r\n<p><span style=\"font-size:12pt\"><span style=\"font-family:&quot;Times New Roman&quot;,serif\">3) onların konturları silinmişdir,</span></span></p>\r\n\r\n<p><span style=\"font-size:12pt\"><span style=\"font-family:&quot;Times New Roman&quot;,serif\">4) Bəzən bir şəkil və ya cisim g&ouml;z&uuml;n&uuml;zdə qoşa şəkildə g&ouml;r&uuml;nə bilər.</span></span></p>\r\n\r\n<p><span style=\"font-size:12pt\"><span style=\"font-family:&quot;Times New Roman&quot;,serif\">Bundan əlavə, &ccedil;ox vaxt xəstələrdə işıqdan qorxma hissi yaranır. Və ya onlar bir g&ouml;zləri ilə &ccedil;ox yaxşı g&ouml;r&uuml;rlər, digər g&ouml;zlə isə zəif.<br />\r\n<br />\r\nKataraktanın ilk simptomları ortaya &ccedil;ıxdığı zamandan etibarən m&uuml;ayinə &uuml;&ccedil;&uuml;n m&uuml;raciət etmək və dərhal m&uuml;alicə olunmaq zəruridir.</span></span></p>\r\n\r\n<p style=\"text-align:justify\">&nbsp;</p>", "description_2": "El arasında katarakta xəstəliyinə \"mirvari suyu\" adı verilmişdir.", "image": "blogs/ameliyatsiz-katarakt-tedavisi-34.png", "created": "2024-01-22", "is_home_page": true}}, {"model": "core.blog", "pk": 2, "fields": {"title": "Göz çəpliyinin səbəbi, çəpgözlük", "description": "<p style=\"text-align:justify\"><strong><span style=\"font-size:14pt\"><span style=\"font-family:&quot;Times New Roman&quot;,serif\">G&ouml;z &ccedil;əpliyi </span></span></strong></p>\r\n\r\n<p style=\"text-align:justify\"><span style=\"font-size:14pt\"><span style=\"font-family:&quot;Times New Roman&quot;,serif\">Təbii olaraq, insan g&ouml;z&uuml;ndə meydana gələn hər hansı problem rahat həyat fəaliyyətini məhdudlaşdırır. &Ccedil;&uuml;nki bu zaman g&ouml;rə bildiklərimiz də məhdudlaşır. Goz cepliyi &ndash; cepgozluk kimi g&ouml;z narahatlıqları fiziki g&ouml;r&uuml;n&uuml;ş baxımından da pasiyentləri narahat etməkdədir.</span></span></p>\r\n\r\n<p style=\"text-align:justify\"><strong><span style=\"font-size:14pt\"><span style=\"font-family:&quot;Times New Roman&quot;,serif\">&Ccedil;əpg&ouml;zl&uuml;k nəyə deyilir?</span></span></strong></p>\r\n\r\n<p style=\"text-align:justify\"><span style=\"font-size:14pt\"><span style=\"font-family:&quot;Times New Roman&quot;,serif\">Bunu sadə dildə izah etsək, &ccedil;əpg&ouml;zl&uuml;yə iki g&ouml;z arasında olan uyğunsuzluq deyə bilərik. Belə ki, sağlam g&ouml;zlər bir-birinə uyğun, paralel şəkildə g&ouml;r&uuml;n&uuml;r və g&ouml;z hərəkəti də buna uyğunlaşır. &Ccedil;əpg&ouml;zl&uuml;k olan insanlar da isə g&ouml;zlərin biri d&uuml;z baxarkən digəri aşağıya, yuxarıya və s. baxmış olur. Bəzən daha ağır simptomları olanlarda g&ouml;zlərin hər ikisində bunu m&uuml;şahidə edə bilirik. </span></span></p>\r\n\r\n<p style=\"text-align:justify\"><span style=\"font-size:14pt\"><span style=\"font-family:&quot;Times New Roman&quot;,serif\">&Ccedil;əpg&ouml;zl&uuml;k uşaqlıqda &ouml;z&uuml;n&uuml; g&ouml;stərən və m&uuml;daxilə edilmədikdə qalıcı ola bilən bir g&ouml;z xəstəliyidir. </span></span></p>\r\n\r\n<p style=\"text-align:justify\">&nbsp;</p>\r\n\r\n<p style=\"text-align:justify\"><span style=\"font-size:14pt\"><span style=\"font-family:&quot;Times New Roman&quot;,serif\">Cepgozluk elametleri </span></span></p>\r\n\r\n<p style=\"text-align:justify\">&nbsp;</p>\r\n\r\n<p style=\"text-align:justify\"><span style=\"font-size:14pt\"><span style=\"font-family:&quot;Times New Roman&quot;,serif\">Bunu, əslində, &uuml;zdəki g&ouml;r&uuml;n&uuml;şdən, g&ouml;zlərin hərəkətindən nisbətən sezə bilərsiniz. Amma təbii ki, m&uuml;təxəssis həkim sizin g&ouml;rə bilmədiyiniz ən sadə &ccedil;əpg&ouml;zl&uuml;k əlamətlərini aşkar edəcəkdir. Məhz buna g&ouml;rə uşaq yaşlarından m&uuml;təmadi g&ouml;z m&uuml;ayinələri olduqca vacibdir.</span></span></p>\r\n\r\n<p style=\"text-align:justify\"><span style=\"font-size:14pt\"><span style=\"font-family:&quot;Times New Roman&quot;,serif\">Cepgozluk olan insanlarda g&ouml;r&uuml;lən bir sıra problemlər: </span></span></p>\r\n\r\n<p style=\"text-align:justify\">&nbsp;</p>\r\n\r\n<ul>\r\n\t<li style=\"text-align:justify\"><span style=\"font-size:14pt\"><span style=\"font-family:&quot;Times New Roman&quot;,serif\">G&ouml;zlərdə sulanma</span></span></li>\r\n\t<li style=\"text-align:justify\"><span style=\"font-size:14pt\"><span style=\"font-family:&quot;Times New Roman&quot;,serif\">Baş və g&ouml;z ağrıları</span></span></li>\r\n\t<li style=\"text-align:justify\"><span style=\"font-size:14pt\"><span style=\"font-family:&quot;Times New Roman&quot;,serif\">İkili g&ouml;rmə</span></span></li>\r\n\t<li style=\"text-align:justify\"><span style=\"font-size:14pt\"><span style=\"font-family:&quot;Times New Roman&quot;,serif\">Bulanıq g&ouml;rmə</span></span></li>\r\n\t<li style=\"text-align:justify\"><span style=\"font-size:14pt\"><span style=\"font-family:&quot;Times New Roman&quot;,serif\">Baş və g&ouml;z&uuml; bir tərəfə &ccedil;evirərək baxma</span></span></li>\r\n\t<li style=\"text-align:justify\"><span style=\"font-size:14pt\"><span style=\"font-family:&quot;Times New Roman&quot;,serif\">Tam və rahat şəkildə bir &ccedil;ox bucaqdan g&ouml;rə bilməmək </span></span></li>\r\n</ul>\r\n\r\n<p style=\"text-align:justify\">&nbsp;</p>\r\n\r\n<p style=\"text-align:justify\"><strong><span style=\"font-size:14pt\"><span style=\"font-family:&quot;Times New Roman&quot;,serif\">&Ccedil;əpg&ouml;zl&uuml;k niyə yaranır? </span></span></strong></p>\r\n\r\n<p style=\"text-align:justify\">&nbsp;</p>\r\n\r\n<p style=\"text-align:justify\"><span style=\"font-size:14pt\"><span style=\"font-family:&quot;Times New Roman&quot;,serif\">&Ccedil;əpg&ouml;zl&uuml;k hansı səbəbdən yaranır? Cepgozluyun sebebleri nelerdir? G&ouml;z&uuml;n aşağı, yuxarı, sağa və sola hərəkət etməsində rol oynayan əzələ qrupunun bir və ya bir ne&ccedil;əsində q&uuml;vvətin azalması və ya artması nəticəsində bu əzələlər arasında uyğunsuzluq ortaya &ccedil;ıxmış olur. Bu da &ccedil;əpg&ouml;zl&uuml;yə səbəb olan problemlərdəndir. Bundan başqa: </span></span></p>\r\n\r\n<p style=\"text-align:justify\">&nbsp;</p>\r\n\r\n<ul>\r\n\t<li style=\"text-align:justify\"><span style=\"font-size:14pt\"><span style=\"font-family:&quot;Times New Roman&quot;,serif\">Genetik faktorlar</span></span></li>\r\n\t<li style=\"text-align:justify\"><span style=\"font-size:14pt\"><span style=\"font-family:&quot;Times New Roman&quot;,serif\">Beyin iflici</span></span></li>\r\n\t<li style=\"text-align:justify\"><span style=\"font-size:14pt\"><span style=\"font-family:&quot;Times New Roman&quot;,serif\">Daun sindromu</span></span></li>\r\n\t<li style=\"text-align:justify\"><span style=\"font-size:14pt\"><span style=\"font-family:&quot;Times New Roman&quot;,serif\">Uşaqlıq d&ouml;vr&uuml;ndə ke&ccedil;irilən bəzi xəstəliklər, travmalar və ya zədələr</span></span></li>\r\n\t<li style=\"text-align:justify\"><span style=\"font-size:14pt\"><span style=\"font-family:&quot;Times New Roman&quot;,serif\">Beyin şişləri və s. </span></span></li>\r\n</ul>\r\n\r\n<p style=\"text-align:justify\">&nbsp;</p>\r\n\r\n<p style=\"text-align:justify\"><span style=\"font-size:14pt\"><span style=\"font-family:&quot;Times New Roman&quot;,serif\">Cepgozluk sebeblerinden hesab olunur.</span></span></p>\r\n\r\n<p style=\"text-align:justify\">&nbsp;</p>\r\n\r\n<p style=\"text-align:justify\"><strong><span style=\"font-size:14pt\"><span style=\"font-family:&quot;Times New Roman&quot;,serif\">&Ccedil;əpg&ouml;zl&uuml;y&uuml;n m&uuml;alicəsi </span></span></strong></p>\r\n\r\n<p style=\"text-align:justify\"><span style=\"font-size:14pt\"><span style=\"font-family:&quot;Times New Roman&quot;,serif\">M&uuml;asir d&ouml;vr&uuml;m&uuml;zdə &ccedil;əpg&ouml;zl&uuml;y&uuml;n m&uuml;alicəsi &uuml;&ccedil;&uuml;n m&uuml;daxilə &uuml;sulları imkan verir ki, illər əvvəl tibbin imkanlarından yararlana bilməyən insanlardan fərqli olaraq kimi bu g&uuml;n&uuml;n uşaqları komplekssiz həyat s&uuml;rs&uuml;nlər.</span></span></p>\r\n\r\n<p style=\"text-align:justify\"><span style=\"font-size:14pt\"><span style=\"font-family:&quot;Times New Roman&quot;,serif\">&Ccedil;əpg&ouml;zl&uuml;k problemindən dolayı m&uuml;raciət edən və tam uğurlu əməliyyat ilə sağlam və rahat g&ouml;rməsinə qovuşdurduğum y&uuml;zlərlə pasiyentim var. &Ccedil;ox xoşbəxtəm ki, onlar həm fiziki g&ouml;r&uuml;n&uuml;şlərindən məmnun qalırlar, həm də rahat g&ouml;rməkdən z&ouml;vq alaraq evlərinə qayıdırlar.</span></span></p>\r\n\r\n<p style=\"text-align:justify\">&nbsp;</p>\r\n\r\n<p style=\"text-align:justify\">&nbsp;</p>", "description_2": "Bunu sadə dildə izah etsək, çəpgözlüyə iki göz arasında olan uyğunsuzluq deyə bilərik.", "image": "blogs/cepgozluk-123-usaqlarda-cepgozluk-emeliyyati_2.png", "created": "2024-01-22", "is_home_page": true}}, {"model": "core.blog", "pk": 4, "fields": {"title": "Uşaqlarda göz xəstəlikləri", "description": "<p style=\"text-align:justify\">&nbsp;</p>\r\n\r\n<p style=\"text-align:justify\"><span style=\"font-size:14pt\"><span style=\"font-family:&quot;Times New Roman&quot;,serif\"><strong><span dir=\"ltr\" lang=\"AZ-LATIN\" style=\"font-family:&quot;Calibri&quot;,sans-serif\">Uşaqlarda g&ouml;z zəifliyi</span></strong></span></span></p>\r\n\r\n<p style=\"text-align:justify\"><span style=\"font-size:14pt\"><span style=\"font-family:&quot;Times New Roman&quot;,serif\"><span dir=\"ltr\" lang=\"AZ-LATIN\" style=\"font-family:&quot;Calibri&quot;,sans-serif\">Demək olar ki, g&ouml;z xəstəliklərinin əksəriyyəti genetikdir. Uşaqlarda da anadangəlmə g&ouml;z zəifliyi &ndash; g&ouml;z xəstəlikləri bundan qaynaqlanır. Bundan əlavə, uşaqlarda ən geniş yayılan g&ouml;z zəifliklərindən birinin miopiya olduğunu qeyd edə bilərik. Bunun isə m&uuml;xtəlif səbəbləri var. &Ccedil;&uuml;nki m&uuml;asir d&ouml;vr&uuml;n uşaqları, gəncləri, eləcə də b&ouml;y&uuml;klər internetsiz &ndash; telefon, komp&uuml;ter və planşetsiz nə işlərini rahat şəkildə g&ouml;rə bilirlər, nə də boş vaxtlarını bu əşyalar olmadan ke&ccedil;irə bilirlər.</span></span></span></p>\r\n\r\n<p style=\"text-align:justify\"><span style=\"font-size:14pt\"><span style=\"font-family:&quot;Times New Roman&quot;,serif\"><span dir=\"ltr\" lang=\"AZ-LATIN\" style=\"font-family:&quot;Calibri&quot;,sans-serif\">Usaqlarda miopiya. K&ouml;rpələr isə telefon və planşetdə oyun oynamağı sevirlər və onlarda miopiya (uzağı g&ouml;rmənin zəifləməsi, uzağı g&ouml;rə bilməmək) inkişaf edir. Onlar artıq məsafə artdıqca m&ouml;vcud olan əşyaları bulanıq g&ouml;rməyə başlayır. İndi demək olar ki, hər k&ouml;rpədə miopiyanın yaranması riski var.</span></span></span></p>\r\n\r\n<p style=\"text-align:justify\">&nbsp;</p>\r\n\r\n<p style=\"text-align:justify\"><span style=\"font-size:14pt\"><span style=\"font-family:&quot;Times New Roman&quot;,serif\"><strong><span dir=\"ltr\" lang=\"AZ-LATIN\" style=\"font-family:&quot;Calibri&quot;,sans-serif\">Erken dogulmus usaqlarda goz xesteliyi</span></strong></span></span></p>\r\n\r\n<p style=\"text-align:justify\"><span style=\"font-size:14pt\"><span style=\"font-family:&quot;Times New Roman&quot;,serif\"><span dir=\"ltr\" lang=\"AZ-LATIN\" style=\"font-family:&quot;Calibri&quot;,sans-serif\">Erkən doğulmuş korpelerde m&uuml;əyyən g&ouml;z xəstəlikləri riski var. Belə ki, yarım&ccedil;ıq doğulmuş uşaqlarda <span style=\"background-color:white\"><span style=\"color:black\">retinopatiya adlandırılan g&ouml;z xəstəliyi m&ouml;vcud ola bilir. </span></span></span><span style=\"background-color:white\"><span style=\"font-family:&quot;Calibri&quot;,sans-serif\"><span style=\"color:black\">Retinopatiya &ndash; torlu qişa xəstəliyidir</span></span></span><span style=\"background-color:white\"><span style=\"font-family:&quot;Calibri&quot;,sans-serif\"><span style=\"color:black\">. Retinopatiya aşağıdakı </span></span></span><span style=\"background-color:white\"><span style=\"font-family:&quot;Calibri&quot;,sans-serif\"><span style=\"color:black\">səbəblərdən yaran</span></span></span><span style=\"background-color:white\"><span style=\"font-family:&quot;Calibri&quot;,sans-serif\"><span style=\"color:black\">a bilər</span></span></span><span style=\"background-color:white\"><span style=\"font-family:&quot;Calibri&quot;,sans-serif\"><span style=\"color:black\">:</span></span></span></span></span></p>\r\n\r\n<p style=\"text-align:justify\">&nbsp;</p>\r\n\r\n<ul>\r\n\t<li style=\"text-align:justify\"><span style=\"font-size:14pt\"><span style=\"font-family:&quot;Times New Roman&quot;,serif\"><span style=\"background-color:white\"><span style=\"font-family:&quot;Calibri&quot;,sans-serif\"><span style=\"color:black\">damarların normal inkişafının dayanması,</span></span></span></span></span></li>\r\n\t<li style=\"text-align:justify\"><span style=\"font-size:14pt\"><span style=\"font-family:&quot;Times New Roman&quot;,serif\"><span style=\"background-color:white\"><span style=\"font-family:&quot;Calibri&quot;,sans-serif\"><span style=\"color:black\">patoloji damarların inkişafı,</span></span></span></span></span></li>\r\n\t<li style=\"text-align:justify\"><span style=\"font-size:14pt\"><span style=\"font-family:&quot;Times New Roman&quot;,serif\"><span style=\"background-color:white\"><span style=\"font-family:&quot;Calibri&quot;,sans-serif\"><span style=\"color:black\">fibroz toxumanın əmələ gəlməsi</span></span></span></span></span></li>\r\n</ul>\r\n\r\n<p style=\"margin-left:95px; text-align:justify\">&nbsp;</p>\r\n\r\n<p style=\"text-align:justify\"><span style=\"font-size:14pt\"><span style=\"font-family:&quot;Times New Roman&quot;,serif\"><span dir=\"ltr\" lang=\"AZ-LATIN\" style=\"font-family:&quot;Calibri&quot;,sans-serif\">Doğuş yollarında infeksiya (anada, hamiləlik m&uuml;ddətində və ya hamiləliyə qədərki d&ouml;vrdə və s.) olduğu zaman və ya ana cinsi infeksiyaya yoluxubsa, k&ouml;rpənin g&ouml;z xəstəliyi ilə doğulma riski var. K&ouml;rpənin g&ouml;z&uuml;ndə tez-tez &ccedil;irklənmə, qızarıqlıq, qaşıntı varsa, nəzərə alın ki, bu g&ouml;z infeksiyanın və ya hər hansı g&ouml;z xəstəliyinin əlaməti ola bilər. Eyni zamanda g&ouml;z yaşı burun kanalı tıxanıqlığı probleminin olması da uşaqlarda g&ouml;z &ccedil;irklənməsinə gətirib &ccedil;ıxarır. </span></span></span></p>\r\n\r\n<p style=\"text-align:justify\"><span style=\"font-size:14pt\"><span style=\"font-family:&quot;Times New Roman&quot;,serif\"><span dir=\"ltr\" lang=\"AZ-LATIN\" style=\"font-family:&quot;Calibri&quot;,sans-serif\">Məhz buna g&ouml;rə k&ouml;rpələrin və uşaqların davamlı g&ouml;z m&uuml;ayinəsinə gətirilməsi vacibdir, &ccedil;&uuml;nki uşaqlar g&ouml;zlərində olan hər hansı narahatlığı tam m&uuml;əyyən edə bilmirlər və ya dilə gətirməkdən &ccedil;əkinirlər.</span></span></span></p>\r\n\r\n<p style=\"text-align:justify\">&nbsp;</p>", "description_2": "Demək olar ki, göz xəstəliklərinin əksəriyyəti genetikdir. Uşaqlarda", "image": "blogs/usaqlarda-goz-xestelikleri234.png", "created": "2024-01-22", "is_home_page": true}}, {"model": "core.blog", "pk": 5, "fields": {"title": "Miopiya, miopiyanın qarşısını almaq mümkündürmü?", "description": "<p style=\"text-align:justify\"><strong><span style=\"font-size:14pt\"><span style=\"font-family:&quot;Times New Roman&quot;,serif\">Miopiya nedir?</span></span></strong></p>\r\n\r\n<p style=\"text-align:justify\"><span style=\"font-size:14pt\"><span style=\"font-family:&quot;Times New Roman&quot;,serif\">Artıq demək olar ki, d&uuml;nya əhalisinin yarısı uzağı g&ouml;rə bilməmək problemindən &ndash; miopiyadan əziyyət &ccedil;əkir. Miopiya niye yaranir? G&ouml;zlərində miopiya olan insanlar yaxınlıqdakı əşyaları və insanları, ətraf m&uuml;hiti &ccedil;ox yaxşı g&ouml;rə bilsələr də, bu cisimlər uzaqlaşdıqca bulanıq g&ouml;r&uuml;rlər və ya &ccedil;oz zəif g&ouml;r&uuml;rlər. (Təbii ki, məsafənin artması g&ouml;rməni daha da &ccedil;ətinləşdirir). Qısaca, miopoya uzagi gore bilmemekdir.</span></span></p>\r\n\r\n<p style=\"text-align:justify\"><strong><span style=\"font-size:14pt\"><span style=\"font-family:&quot;Times New Roman&quot;,serif\">Uzagi gore bilmemek, miopiya niye olur? </span></span></strong></p>\r\n\r\n<p style=\"text-align:justify\"><span style=\"font-size:14pt\"><span style=\"font-family:&quot;Times New Roman&quot;,serif\">G&ouml;z oxunun normadan uzun olması, genetika amili, uzunm&uuml;ddətli yaxına baxmaq (telefona baxmaq, kitab &ccedil;ox oxumaq və s.) və digər faktorlar miopiya yaradan esas sebeblerdendir. Ən &ccedil;ox məktəbyaşlı uşaqlarda &ouml;z&uuml;n&uuml; g&ouml;stərir. </span></span></p>\r\n\r\n<p style=\"text-align:justify\">&nbsp;</p>\r\n\r\n<p style=\"text-align:justify\"><strong><span style=\"font-size:14pt\"><span style=\"font-family:&quot;Times New Roman&quot;,serif\">Miopiyanın əlamətləri:</span></span></strong></p>\r\n\r\n<p style=\"text-align:justify\">&nbsp;</p>\r\n\r\n<ul>\r\n\t<li style=\"text-align:justify\"><span style=\"font-size:14pt\"><span style=\"font-family:&quot;Times New Roman&quot;,serif\">televizora, hətta bəzən 30sm-dən artıq məsafəyə g&ouml;zləri qıyaraq baxma (bu, zamanla baş ağrısına da səbəb ola bilir)</span></span></li>\r\n\t<li style=\"text-align:justify\"><span style=\"font-size:14pt\"><span style=\"font-family:&quot;Times New Roman&quot;,serif\">maşın s&uuml;rərkən yolu g&ouml;rməkdə &ccedil;ətinlik &ccedil;əkmə (x&uuml;susilə də gecələr)</span></span></li>\r\n\t<li style=\"text-align:justify\"><span style=\"font-size:14pt\"><span style=\"font-family:&quot;Times New Roman&quot;,serif\">nisbətən uzaqda &ndash; digər insanların rahatlıqla g&ouml;rə bildiyi yazıları, işarələri, şəkilləri və s. bulanıq g&ouml;rmək</span></span></li>\r\n\t<li style=\"text-align:justify\"><span style=\"font-size:14pt\"><span style=\"font-family:&quot;Times New Roman&quot;,serif\">arada bir hiss olunan g&ouml;z ağrıları</span></span></li>\r\n</ul>\r\n\r\n<p style=\"text-align:justify\">&nbsp;</p>\r\n\r\n<p style=\"text-align:justify\"><span style=\"font-size:14pt\"><span style=\"font-family:&quot;Times New Roman&quot;,serif\">Uşaqlarda miopiya </span></span></p>\r\n\r\n<p style=\"text-align:justify\">&nbsp;</p>\r\n\r\n<p style=\"text-align:justify\"><span style=\"font-size:14pt\"><span style=\"font-family:&quot;Times New Roman&quot;,serif\">Usaqlarda miopiya elametlerini nece mueyyenlesdirmek olar? Uşaqlar, əslində, g&ouml;zlərinin zəiflədiklərini hiss etmirlər. Ya da hiss etdikləri təqdirdə valideynlərinə bunu dilə gətirməyə &ccedil;əkinir və ya qorxurlar. Bəs uşaqlarda miopiya olduğunu necə aşkar edə bilərsiniz? &ndash; Təbii ki, bunu dəqiqləşdirmək &uuml;&ccedil;&uuml;n oftalmoloq həkim m&uuml;ayinəsi vacibdir. Lakin aşağıdakı əlamətləri oxuyaraq da məlumatlana və &ouml;vladınızın g&ouml;z sağlamlığını qorumaq &uuml;&ccedil;&uuml;n tez addım ata bilərsiniz.</span></span></p>\r\n\r\n<p style=\"text-align:justify\">&nbsp;</p>\r\n\r\n<ul>\r\n\t<li style=\"text-align:justify\"><span style=\"font-size:14pt\"><span style=\"font-family:&quot;Times New Roman&quot;,serif\">Belə uşaqlar daima televizorun ən yaxınında əyləşir, uzaqdan TV-yə baxmaq istəmirlər</span></span></li>\r\n\t<li style=\"text-align:justify\"><span style=\"font-size:14pt\"><span style=\"font-family:&quot;Times New Roman&quot;,serif\">Tez-tez g&ouml;zlərini qırpırlar</span></span></li>\r\n\t<li style=\"text-align:justify\"><span style=\"font-size:14pt\"><span style=\"font-family:&quot;Times New Roman&quot;,serif\">G&ouml;zlərini ovuşdurmaq vərdişindən imtina etmirlər</span></span></li>\r\n\t<li style=\"text-align:justify\"><span style=\"font-size:14pt\"><span style=\"font-family:&quot;Times New Roman&quot;,serif\">Uzaqda m&ouml;vcud olan əşyaların fərqində olmadan hərəkət edirlər və s.</span></span></li>\r\n</ul>\r\n\r\n<p style=\"text-align:justify\">&nbsp;</p>\r\n\r\n<p style=\"text-align:justify\"><strong><span style=\"font-size:14pt\"><span style=\"font-family:&quot;Times New Roman&quot;,serif\">Miopiyanın qarsisini nece almaq olar?</span></span></strong></p>\r\n\r\n<p style=\"text-align:justify\"><span style=\"font-size:14pt\"><span style=\"font-family:&quot;Times New Roman&quot;,serif\">Miopiyanın qarşısını almaq m&uuml;mk&uuml;nd&uuml;rm&uuml;? Əvvəlcə, m&uuml;ayinə olunaraq g&ouml;z sağlamlığınızın hansı dərəcədə olmasından əmin olmağınızda fayda var. </span></span></p>\r\n\r\n<p style=\"text-align:justify\"><span style=\"font-size:14pt\"><span style=\"font-family:&quot;Times New Roman&quot;,serif\">Miopiyanın qarşısını almaq indiki zamanda hər kəs &uuml;&ccedil;&uuml;n əziyyətli bir prosesdir. &Ccedil;&uuml;nki demək olar ki, hamımız texnologiyanın k&ouml;məyi olmadan &ccedil;alışa bilmirik.<br />\r\nOna g&ouml;rə də g&uuml;n ərzində daim ekran qarşısında olan insanlar &uuml;&ccedil;&uuml;n bir ne&ccedil;ə ki&ccedil;ik t&ouml;vsiyəm var: </span></span></p>\r\n\r\n<ol>\r\n\t<li style=\"text-align:justify\"><span style=\"font-size:14pt\"><span style=\"font-family:&quot;Times New Roman&quot;,serif\">Komp&uuml;ter, telefon və s.- baxdığınız zaman hər 20 dəqiqədən bir g&ouml;zlərinizi uzaq məsafəyə dikərək baxın və g&ouml;zlərinizi qırpın.</span></span></li>\r\n\t<li style=\"text-align:justify\"><span style=\"font-size:14pt\"><span style=\"font-family:&quot;Times New Roman&quot;,serif\">Belə zamanlarda g&ouml;zlərinizi istirahıət etdirmək &uuml;&ccedil;&uuml;n hər iki əlinizi g&ouml;zlərinizə tutaraq (bu zaman he&ccedil; işıq g&ouml;rməməlisiniz, əllərinizi tam tutmalısınız) 20 saniyə ərzində g&ouml;zləyin, daha sonra g&ouml;zlərinizi a&ccedil;ın. Bunu kitab oxuyarkən də g&ouml;zlərinizə tətbiq edə bilərsiniz.</span></span></li>\r\n\t<li style=\"text-align:justify\"><span style=\"font-size:14pt\"><span style=\"font-family:&quot;Times New Roman&quot;,serif\">Yuxu rejiminizin tam olması g&ouml;zlərinizin yorğunluğunu aradan qaldıracaq. </span></span></li>\r\n\t<li style=\"text-align:justify\"><span style=\"font-size:14pt\"><span style=\"font-family:&quot;Times New Roman&quot;,serif\">Zərərli ş&uuml;aları olan əşyaları istifadə etdikdə ən azı 30 sm məsafə saxlamalısınız.</span></span></li>\r\n</ol>\r\n\r\n<p style=\"text-align:justify\">&nbsp;</p>\r\n\r\n<p style=\"text-align:justify\"><span style=\"font-size:14pt\"><span style=\"font-family:&quot;Times New Roman&quot;,serif\">Əgər artıq sizdə miopiya aşkarlanıbsa, narahat olmayın. Eynək ş&uuml;şələrini, linzaları tez-tez dəyişdirmək məcburiyyətində deyilsiniz və ya zəif g&ouml;rən g&ouml;zlərlə yaşamaq. Miopiya artıq en son lazer texnologiyaları aradan qalxa bilən adi bir problemə &ccedil;evrilib. Miopiyanın m&uuml;alicəsi məhz bu səbəbdən m&uuml;mk&uuml;nd&uuml;r.</span></span></p>\r\n\r\n<p style=\"text-align:justify\"><span style=\"font-size:14pt\"><span style=\"font-family:&quot;Times New Roman&quot;,serif\">G&ouml;zlərinizə yaxşı baxın.</span></span></p>", "description_2": "Artıq demək olar ki, dünya əhalisinin yarısı uzağı görə bilməmək problemindən", "image": "blogs/miopiyanin-tam-mualicesi.webp.png", "created": "2024-01-22", "is_home_page": false}}, {"model": "core.gallery", "pk": 1, "fields": {"title": "Gözdə yanma, qaşınma varsa, bunları edin!", "image": "gallery/Gözlərdə_yanma_qaşınma.PNG", "youtube_link": "https://www.youtube.com/watch?v=6as7Hg-42w8"}}, {"model": "core.gallery", "pk": 2, "fields": {"title": "Linzalardan düzgün istifadə qaydaları!", "image": "gallery/linzaların_gözlərə_ziyanı.PNG", "youtube_link": "https://www.youtube.com/watch?v=IaUkTZo61NA"}}, {"model": "core.gallery", "pk": 3, "fields": {"title": "Qara su xəstəliyinin əlamətləri l Qlaukoma", "image": "gallery/qara_su.PNG", "youtube_link": "https://www.youtube.com/watch?v=Wn5rtzossKs"}}, {"model": "core.gallery", "pk": 4, "fields": {"title": "Çəpgözlər iki yox, bir görürlər! l Uşaqlarda çəplik", "image": "gallery/çəpgözlük.PNG", "youtube_link": "https://www.youtube.com/watch?v=qCKynPvenPA"}}, {"model": "core.gallery", "pk": 5, "fields": {"title": "Uşaqlarda gizli çəplik əlamətlərinə diqqət!", "image": "gallery/gizli_çəplik.PNG", "youtube_link": "https://www.youtube.com/watch?v=9TkfciuPuDY"}}, {"model": "core.gallery", "pk": 6, "fields": {"title": "Göz əməliyyatları içində ən yaxşısı: \"SMİLE\"", "image": "gallery/smile.PNG", "youtube_link": "https://www.youtube.com/watch?v=pjE3lrYJ_a0"}}, {"model": "core.appointment", "pk": 1, "fields": {"name": "Ilgar Hasanzada", "email": "ilqarhsnzad@gmail.com", "date": "2024-01-08"}}, {"model": "core.appointment", "pk": 2, "fields": {"name": "Ilgar Hasanzada", "email": "ilqarhsnzad@gmail.com", "date": "2024-01-08"}}, {"model": "core.appointment", "pk": 3, "fields": {"name": "user1", "email": "ilqarhsnzad@gmail.com", "date": "2024-01-24"}}, {"model": "core.appointment", "pk": 4, "fields": {"name": "Ilgar", "email": "ilqarhsnzad@gmail.com", "date": "2024-01-24"}}, {"model": "core.appointment", "pk": 5, "fields": {"name": "Ilgar", "email": "ilqarhsnzad@gmail.com", "date": "2024-01-25"}}]